[
  {
    "id": "test-dummy-launch",
    "cardName": "[TEST] Dummy Rewards Credit Card",
    "issuerName": "SBI Card",
    "issuerSlug": "sbi-card",
    "officialUrl": "https://www.sbicard.com/",
    "productPageUrl": "https://www.sbicard.com/en/personal/credit-cards/simplyclick-sbi-card.html",
    "discoveredAt": "2026-07-10T12:00:00.000Z",
    "lastmod": "2026-07-09",
    "announcement": {
      "title": "SBI Card launches new Dummy Rewards Credit Card (example announcement)",
      "url": "https://www.sbicard.com/en/personal/credit-cards/simplyclick-sbi-card.html",
      "description": "This is placeholder announcement text to show how a real search result snippet would render in this section."
    },
    "community": {
      "reddit": {
        "title": "[Example] Anyone got the new Dummy Rewards Card?",
        "url": "https://www.reddit.com/r/CreditCardsIndia/",
        "description": "Placeholder Reddit thread snippet for layout testing."
      },
      "twitter": {
        "title": "Example tweet about the Dummy Rewards Card",
        "url": "https://x.com/search?q=dummy%20rewards%20card",
        "description": "Placeholder X/Twitter result for layout testing."
      },
      "youtube": {
        "title": "Dummy Rewards Card - Full Review (Example)",
        "url": "https://www.youtube.com/results?search_query=dummy+rewards+card",
        "description": "Placeholder YouTube result for layout testing."
      }
    }
  }
]
